openadapt/__init__.py
openadapt/cli.py
openadapt/config.py
openadapt/version.py
openadapt-1.0.0.dist-info/METADATA
openadapt-1.0.0.dist-info/WHEEL
openadapt-1.0.0.dist-info/entry_points.txt
openadapt-1.0.0.dist-info/licenses/LICENSE
openadapt-1.0.0.dist-info/RECORD
