Metadata-Version: 2.4
Name: openadapt
Version: 1.0.0
Summary: GUI automation with ML - record, train, deploy, evaluate
Project-URL: Homepage, https://openadapt.ai
Project-URL: Documentation, https://docs.openadapt.ai
Project-URL: Repository, https://github.com/OpenAdaptAI/openadapt
Project-URL: Bug Tracker, https://github.com/OpenAdaptAI/openadapt/issues
Author-email: "MLDSAI Inc." <richard@mldsai.com>
License-Expression: MIT
License-File: LICENSE
Keywords: agent,automation,computer-use,gui,ml,rpa,vlm
Classifier: Development Status :: 4 - Beta
Classifier: Intended Audience :: Developers
Classifier: Intended Audience :: Science/Research
Classifier: License :: OSI Approved :: MIT License
Classifier: Programming Language :: Python :: 3
Classifier: Programming Language :: Python :: 3.10
Classifier: Programming Language :: Python :: 3.11
Classifier: Programming Language :: Python :: 3.12
Classifier: Topic :: Scientific/Engineering :: Artificial Intelligence
Classifier: Topic :: Software Development :: Libraries :: Python Modules
Requires-Python: >=3.10
Requires-Dist: click>=8.0.0
Provides-Extra: all
Requires-Dist: openadapt-capture>=0.1.0; extra == 'all'
Requires-Dist: openadapt-evals>=0.1.0; extra == 'all'
Requires-Dist: openadapt-grounding>=0.1.0; extra == 'all'
Requires-Dist: openadapt-ml>=0.2.0; extra == 'all'
Requires-Dist: openadapt-privacy>=0.1.0; extra == 'all'
Requires-Dist: openadapt-retrieval>=0.1.0; extra == 'all'
Requires-Dist: openadapt-viewer>=0.1.0; extra == 'all'
Provides-Extra: capture
Requires-Dist: openadapt-capture>=0.1.0; extra == 'capture'
Provides-Extra: core
Requires-Dist: openadapt-capture>=0.1.0; extra == 'core'
Requires-Dist: openadapt-evals>=0.1.0; extra == 'core'
Requires-Dist: openadapt-ml>=0.2.0; extra == 'core'
Requires-Dist: openadapt-viewer>=0.1.0; extra == 'core'
Provides-Extra: dev
Requires-Dist: pytest>=8.0.0; extra == 'dev'
Requires-Dist: ruff>=0.1.0; extra == 'dev'
Provides-Extra: evals
Requires-Dist: openadapt-evals>=0.1.0; extra == 'evals'
Provides-Extra: grounding
Requires-Dist: openadapt-grounding>=0.1.0; extra == 'grounding'
Provides-Extra: ml
Requires-Dist: openadapt-ml>=0.2.0; extra == 'ml'
Provides-Extra: privacy
Requires-Dist: openadapt-privacy>=0.1.0; extra == 'privacy'
Provides-Extra: retrieval
Requires-Dist: openadapt-retrieval>=0.1.0; extra == 'retrieval'
Provides-Extra: viewer
Requires-Dist: openadapt-viewer>=0.1.0; extra == 'viewer'
